{"type": "Feature", "id": 12513750, "geometry": {"type": "Point", "coordinates": [47.884499, 39.597698]}, "properties": {"woe:id": 12513750, "woe:parent_id": 2255028, "woe:name": "Parssabad Airport", "woe:placetype": 14, "woe:placetype_name": "Airport", "woe:lang": "ENG", "iso:country": "IR", "meta:provider": ["geoplanet:7.3.1", "geoplanet:7.3.2", "geoplanet:7.4.0", "geoplanet:7.4.1", "geoplanet:7.5.1", "geoplanet:7.5.2", "geoplanet:7.6.0", "geoplanet:7.8.1", "geoplanet:7.9.0", "geoplanet:7.10.0", "geoplanet:8.0.0", "woeplanet:8.0.0"], "meta:indexed": "2020-08-20T20:20:42.428251", "meta:updated": "2020-10-14T12:05:20.298618", "woe:hierarchy": {"continent": 24865671, "country": 23424851, "town": 0, "planet": 1, "county": 0, "suburb": 0, "state": 20070198, "region": 0, "localadmin": 0}, "woe:timezone_id": 28350859, "woe:hash": "tp4138s3m9ym", "woe:centroid": [47.884499, 39.597698], "geom:latitude": 39.597698, "geom:longitude": 47.884499, "geom:hash": "tp4138s3m9ym", "woe:latitude": 39.597698, "geom:centroid": [47.884499, 39.597698], "woe:longitude": 47.884499, "woe:repo": "woeplanet-airport-ir", "geom:area": 0.0, "woe:scale": 19}}