{"type": "Feature", "id": 12513713, "properties": {"woe:id": 12513713, "woe:parent_id": 2246381, "woe:name": "Darrahi Airport", "woe:placetype": 14, "woe:placetype_name": "Airport", "woe:lang": "ENG", "iso:country": "IR", "meta:provider": ["geoplanet:7.3.1", "geoplanet:7.3.2", "geoplanet:7.4.0", "geoplanet:7.4.1", "geoplanet:7.5.1", "geoplanet:7.5.2", "geoplanet:7.6.0", "geoplanet:7.8.1", "geoplanet:7.9.0", "geoplanet:7.10.0", "geoplanet:8.0.0", "woeplanet:8.0.0"], "meta:indexed": "2020-08-20T20:20:42.399632", "meta:updated": "2020-08-22T01:56:00.074131", "woe:hierarchy": {"continent": 24865671, "country": 23424851, "town": 0, "planet": 1, "county": 0, "suburb": 0, "state": 2345781, "region": 0, "localadmin": 0}, "woe:timezone_id": 28350859, "woe:hash": "tjhr45fg9tdg", "woe:centroid": [51.068298, 29.376699], "geom:latitude": 29.376699, "geom:longitude": 51.068298, "geom:hash": "tjhr45fg9tdg", "woe:latitude": 29.376699, "geom:centroid": [51.068298, 29.376699], "woe:longitude": 51.068298, "woe:repo": "woeplanet-airport-ir"}, "geometry": {"coordinates": [51.068298, 29.376699], "type": "Point"}}