{"type": "Feature", "id": 12513716, "geometry": {"type": "Point", "coordinates": [48.1847, 32.4039]}, "properties": {"woe:id": 12513716, "woe:parent_id": 2250677, "woe:name": "Dezful Highway Strip Airport", "woe:placetype": 14, "woe:placetype_name": "Airport", "woe:lang": "ENG", "iso:country": "IR", "meta:provider": ["geoplanet:7.3.1", "geoplanet:7.3.2", "geoplanet:7.4.0", "geoplanet:7.4.1", "geoplanet:7.5.1", "geoplanet:7.5.2", "geoplanet:7.6.0", "geoplanet:7.8.1", "geoplanet:7.9.0", "geoplanet:7.10.0", "geoplanet:8.0.0", "woeplanet:8.0.0"], "meta:indexed": "2020-08-20T20:20:42.401854", "meta:updated": "2020-10-14T12:05:20.298174", "woe:hierarchy": {"continent": 24865671, "country": 23424851, "town": 0, "planet": 1, "county": 0, "suburb": 0, "state": 2345778, "region": 0, "localadmin": 0}, "woe:timezone_id": 28350859, "woe:hash": "tjf226zn2uu2", "woe:centroid": [48.1847, 32.4039], "geom:latitude": 32.4039, "geom:longitude": 48.1847, "geom:hash": "tjf226zn2uu2", "woe:latitude": 32.4039, "geom:centroid": [48.1847, 32.4039], "woe:longitude": 48.1847, "woe:repo": "woeplanet-airport-ir", "geom:area": 0.0, "woe:scale": 19}}