{"type": "Feature", "id": 12513715, "geometry": {"type": "Point", "coordinates": [48.398899, 32.431702]}, "properties": {"woe:id": 12513715, "woe:parent_id": 2254547, "woe:name": "Dezful Airport", "woe:placetype": 14, "woe:placetype_name": "Airport", "woe:lang": "ENG", "iso:country": "IR", "meta:provider": ["geoplanet:7.3.1", "geoplanet:7.3.2", "geoplanet:7.4.0", "geoplanet:7.4.1", "geoplanet:7.5.1", "geoplanet:7.5.2", "geoplanet:7.6.0", "geoplanet:7.8.1", "geoplanet:7.9.0", "geoplanet:7.10.0", "geoplanet:8.0.0", "woeplanet:8.0.0"], "meta:indexed": "2020-08-20T20:20:42.401023", "meta:updated": "2020-10-14T12:05:20.277923", "woe:hierarchy": {"continent": 24865671, "country": 23424851, "town": 0, "planet": 1, "county": 0, "suburb": 0, "state": 2345778, "region": 0, "localadmin": 0}, "woe:timezone_id": 28350859, "woe:hash": "tjf2t250256y", "woe:centroid": [48.398899, 32.431702], "geom:latitude": 32.431702, "geom:longitude": 48.398899, "geom:hash": "tjf2t250256y", "woe:latitude": 32.431702, "geom:centroid": [48.398899, 32.431702], "woe:longitude": 48.398899, "woe:repo": "woeplanet-airport-ir", "geom:area": 0.0, "woe:scale": 19}}