{"type": "Feature", "id": 12513738, "geometry": {"type": "Point", "coordinates": [53.981701, 26.526699]}, "properties": {"woe:id": 12513738, "woe:parent_id": 2236273, "woe:name": "Kish Island Airport", "woe:placetype": 14, "woe:placetype_name": "Airport", "woe:lang": "ENG", "iso:country": "IR", "meta:provider": ["geoplanet:7.3.1", "geoplanet:7.3.2", "geoplanet:7.4.0", "geoplanet:7.4.1", "geoplanet:7.5.1", "geoplanet:7.5.2", "geoplanet:7.6.0", "geoplanet:7.8.1", "geoplanet:7.9.0", "geoplanet:7.10.0", "geoplanet:8.0.0", "woeplanet:8.0.0"], "meta:indexed": "2020-08-20T20:20:42.417840", "woe:alias_ENG_V": ["KIH Airport", "KIH"], "meta:updated": "2020-10-14T12:05:20.264899", "woe:hierarchy": {"continent": 24865671, "country": 23424851, "town": 0, "planet": 1, "county": 0, "suburb": 0, "state": 2345776, "region": 0, "localadmin": 0}, "woe:timezone_id": 28350859, "woe:hash": "thwqumh30z1e", "woe:centroid": [53.981701, 26.526699], "geom:latitude": 26.526699, "geom:longitude": 53.981701, "geom:hash": "thwqumh30z1e", "woe:latitude": 26.526699, "geom:centroid": [53.981701, 26.526699], "woe:longitude": 53.981701, "woe:repo": "woeplanet-airport-ir", "geom:area": 0.0, "woe:scale": 19}}