{"type": "Feature", "id": 12513754, "geometry": {"type": "Point", "coordinates": [57.668098, 28.725599]}, "properties": {"woe:id": 12513754, "woe:parent_id": 2255110, "woe:name": "Sabzevaran Airport", "woe:placetype": 14, "woe:placetype_name": "Airport", "woe:lang": "ENG", "iso:country": "IR", "meta:provider": ["geoplanet:7.3.1", "geoplanet:7.3.2", "geoplanet:7.4.0", "geoplanet:7.4.1", "geoplanet:7.5.1", "geoplanet:7.5.2", "geoplanet:7.6.0", "geoplanet:7.8.1", "geoplanet:7.9.0", "geoplanet:7.10.0", "geoplanet:8.0.0", "woeplanet:8.0.0"], "meta:indexed": "2020-08-20T20:20:42.431807", "meta:updated": "2020-10-14T12:05:20.284633", "woe:hierarchy": {"continent": 24865671, "country": 23424851, "town": 0, "planet": 1, "county": 0, "suburb": 0, "state": 2345788, "region": 0, "localadmin": 0}, "woe:timezone_id": 28350859, "woe:hash": "tm152m2dspf8", "woe:centroid": [57.668098, 28.725599], "geom:latitude": 28.725599, "geom:longitude": 57.668098, "geom:hash": "tm152m2dspf8", "woe:latitude": 28.725599, "geom:centroid": [57.668098, 28.725599], "woe:longitude": 57.668098, "woe:repo": "woeplanet-airport-ir", "geom:area": 0.0, "woe:scale": 19}}