{"type": "Feature", "id": 12513758, "properties": {"woe:id": 12513758, "woe:parent_id": 2225113, "woe:name": "Sarvestan Airport", "woe:placetype": 14, "woe:placetype_name": "Airport", "woe:lang": "ENG", "iso:country": "IR", "meta:provider": ["geoplanet:7.3.1", "geoplanet:7.3.2", "geoplanet:7.4.0", "geoplanet:7.4.1", "geoplanet:7.5.1", "geoplanet:7.5.2", "geoplanet:7.6.0", "geoplanet:7.8.1", "geoplanet:7.9.0", "geoplanet:7.10.0", "geoplanet:8.0.0", "woeplanet:8.0.0"], "meta:indexed": "2020-08-20T20:20:42.435341", "meta:updated": "2020-08-22T01:56:00.091080", "woe:hierarchy": {"continent": 24865671, "country": 23424851, "town": 0, "planet": 1, "county": 0, "suburb": 0, "state": 2345772, "region": 0, "localadmin": 0}, "woe:timezone_id": 28350859, "woe:hash": "tjjy31w5shvy", "woe:centroid": [53.138302, 29.2325], "geom:latitude": 29.2325, "geom:longitude": 53.138302, "geom:hash": "tjjy31w5shvy", "woe:latitude": 29.2325, "geom:centroid": [53.138302, 29.2325], "woe:longitude": 53.138302, "woe:repo": "woeplanet-airport-ir"}, "geometry": {"coordinates": [53.138302, 29.2325], "type": "Point"}}